{
  "parent": "minecraft:recipes/root",
  "rewards": {
    "recipes": [
      "reed"
    ]
  },
  "criteria": {
    "has_reed": {
      "trigger": "minecraft:inventory_changed",
      "conditions": {
        "items": [
          {
            "items": [
              "bloomingnature:reed"
            ]
          }
        ]
      }
    },
    "has_the_recipe": {
      "trigger": "minecraft:recipe_unlocked",
      "conditions": {
        "recipe": "reed"
      }
    }
  },
  "requirements": [
    [
      "has_reed",
      "has_the_recipe"
    ]
  ]
}